paychangu/__init__.py
paychangu/client.py
paychangu/models/payment.py
paychangu/models/payout.py
paychangu/utils/http.py
paychangu-0.0.3.dist-info/LICENSE
paychangu-0.0.3.dist-info/METADATA
paychangu-0.0.3.dist-info/WHEEL
paychangu-0.0.3.dist-info/top_level.txt
paychangu-0.0.3.dist-info/RECORD
