Metadata-Version: 2.1
Name: paychangu
Version: 0.0.3
Summary: Python SDK for PayChangu Level
Author-email: PayChangu <danielonions@paychangu.com>
Project-URL: Homepage, https://github.com/yourusername/paychangu-sdk
Project-URL: Bug Tracker, https://github.com/yourusername/paychangu-sdk/issues
Classifier: Programming Language :: Python :: 3
Classifier: License :: OSI Approved :: MIT License
Classifier: Operating System :: OS Independent
Requires-Python: >=3.7
License-File: LICENSE
Requires-Dist: requests >=2.25.1
